{
    "graph_0": {
        "_type": "graph",
        "format": "torch",
        "nodes": [
            {
                "name": "pool0",
                "id": 140664339498824,
                "class_name": "MaxPool3d(kernel_size=2, stride=2, padding=0, dilation=1, ceil_mode=False)",
                "parameters": [],
                "output_shape": [
                    [
                        42,
                        42,
                        24,
                        24,
                        24
                    ]
                ],
                "num_parameters": []
            },
            {
                "name": "conv1",
                "id": 140662611503984,
                "class_name": "Conv3d(42, 32, kernel_size=(3, 3, 3), stride=(1, 1, 1), padding=(1, 1, 1))",
                "parameters": [
                    [
                        "weight",
                        [
                            32,
                            42,
                            3,
                            3,
                            3
                        ]
                    ],
                    [
                        "bias",
                        [
                            32
                        ]
                    ]
                ],
                "output_shape": [
                    [
                        42,
                        32,
                        24,
                        24,
                        24
                    ]
                ],
                "num_parameters": [
                    36288,
                    32
                ]
            },
            {
                "name": "pool1",
                "id": 140662838849376,
                "class_name": "MaxPool3d(kernel_size=2, stride=2, padding=0, dilation=1, ceil_mode=False)",
                "parameters": [],
                "output_shape": [
                    [
                        42,
                        32,
                        12,
                        12,
                        12
                    ]
                ],
                "num_parameters": []
            },
            {
                "name": "conv2",
                "id": 140662838377608,
                "class_name": "Conv3d(32, 64, kernel_size=(3, 3, 3), stride=(1, 1, 1), padding=(1, 1, 1))",
                "parameters": [
                    [
                        "weight",
                        [
                            64,
                            32,
                            3,
                            3,
                            3
                        ]
                    ],
                    [
                        "bias",
                        [
                            64
                        ]
                    ]
                ],
                "output_shape": [
                    [
                        42,
                        64,
                        12,
                        12,
                        12
                    ]
                ],
                "num_parameters": [
                    55296,
                    64
                ]
            },
            {
                "name": "pool2",
                "id": 140664180430496,
                "class_name": "MaxPool3d(kernel_size=2, stride=2, padding=0, dilation=1, ceil_mode=False)",
                "parameters": [],
                "output_shape": [
                    [
                        42,
                        64,
                        6,
                        6,
                        6
                    ]
                ],
                "num_parameters": []
            },
            {
                "name": "conv3",
                "id": 140664315041216,
                "class_name": "Conv3d(64, 128, kernel_size=(3, 3, 3), stride=(1, 1, 1), padding=(1, 1, 1))",
                "parameters": [
                    [
                        "weight",
                        [
                            128,
                            64,
                            3,
                            3,
                            3
                        ]
                    ],
                    [
                        "bias",
                        [
                            128
                        ]
                    ]
                ],
                "output_shape": [
                    [
                        42,
                        128,
                        6,
                        6,
                        6
                    ]
                ],
                "num_parameters": [
                    221184,
                    128
                ]
            },
            {
                "name": "fc1",
                "id": 140662838468680,
                "class_name": "Linear(in_features=27648, out_features=1, bias=True)",
                "parameters": [
                    [
                        "weight",
                        [
                            1,
                            27648
                        ]
                    ],
                    [
                        "bias",
                        [
                            1
                        ]
                    ]
                ],
                "output_shape": [
                    [
                        42,
                        1
                    ]
                ],
                "num_parameters": [
                    27648,
                    1
                ]
            }
        ],
        "edges": []
    },
    "gradients/conv1.bias": {
        "_type": "histogram",
        "values": [
            1.0,
            0.0,
            0.0,
            0.0,
            0.0,
            0.0,
            0.0,
            0.0,
            0.0,
            0.0,
            0.0,
            0.0,
            0.0,
            1.0,
            0.0,
            0.0,
            0.0,
            2.0,
            0.0,
            1.0,
            0.0,
            0.0,
            1.0,
            2.0,
            2.0,
            3.0,
            0.0,
            1.0,
            1.0,
            1.0,
            0.0,
            1.0,
            0.0,
            1.0,
            0.0,
            0.0,
            2.0,
            2.0,
            0.0,
            0.0,
            3.0,
            2.0,
            0.0,
            0.0,
            0.0,
            0.0,
            1.0,
            0.0,
            1.0,
            0.0,
            0.0,
            0.0,
            1.0,
            0.0,
            0.0,
            0.0,
            0.0,
            0.0,
            0.0,
            0.0,
            0.0,
            0.0,
            0.0,
            2.0
        ],
        "bins": [
            -0.0006805596640333533,
            -0.0006596794701181352,
            -0.000638799334410578,
            -0.0006179191404953599,
            -0.0005970389465801418,
            -0.0005761588108725846,
            -0.0005552786169573665,
            -0.0005343984812498093,
            -0.0005135182873345912,
            -0.000492638093419373,
            -0.0004717579286079854,
            -0.0004508777637965977,
            -0.0004299975698813796,
            -0.00040911740506999195,
            -0.0003882372402586043,
            -0.0003673570463433862,
            -0.0003464768815319985,
            -0.00032559671672061086,
            -0.00030471652280539274,
            -0.0002838363579940051,
            -0.0002629561931826174,
            -0.0002420759992673993,
            -0.00022119583445601165,
            -0.000200315669644624,
            -0.00017943547572940588,
            -0.00015855534002184868,
            -0.00013767514610663056,
            -0.00011679495219141245,
            -9.591481648385525e-05,
            -7.503462256863713e-05,
            -5.415442865341902e-05,
            -3.3274292945861816e-05,
            -1.2394099030643702e-05,
            8.486094884574413e-06,
            2.9366230592131615e-05,
            5.024642450734973e-05,
            7.112661842256784e-05,
            9.200675413012505e-05,
            0.00011288694804534316,
            0.00013376714196056128,
            0.00015464727766811848,
            0.0001755274715833366,
            0.0001964076654985547,
            0.0002172878012061119,
            0.00023816799512133002,
            0.00025904818903654814,
            0.00027992832474410534,
            0.00030080846045166254,
            0.00032168871257454157,
            0.00034256884828209877,
            0.00036344898398965597,
            0.000384329236112535,
            0.0004052093718200922,
            0.0004260895075276494,
            0.00044696975965052843,
            0.00046784989535808563,
            0.0004887300310656428,
            0.0005096102831885219,
            0.0005304904188960791,
            0.0005513705546036363,
            0.0005722508067265153,
            0.0005931309424340725,
            0.0006140110781416297,
            0.0006348913302645087,
            0.0006557714659720659
        ]
    },
    "gradients/fc1.weight": {
        "_type": "histogram",
        "values": [
            1.0,
            0.0,
            0.0,
            0.0,
            1.0,
            0.0,
            1.0,
            0.0,
            0.0,
            1.0,
            0.0,
            0.0,
            1.0,
            1.0,
            0.0,
            0.0,
            1.0,
            1.0,
            0.0,
            0.0,
            0.0,
            0.0,
            3.0,
            0.0,
            1.0,
            2.0,
            0.0,
            1.0,
            1.0,
            1.0,
            3.0,
            3.0,
            3.0,
            4.0,
            3.0,
            6.0,
            7.0,
            7.0,
            11.0,
            5.0,
            6.0,
            14.0,
            12.0,
            15.0,
            11.0,
            18.0,
            16.0,
            22.0,
            34.0,
            39.0,
            57.0,
            45.0,
            56.0,
            69.0,
            80.0,
            111.0,
            154.0,
            197.0,
            275.0,
            354.0,
            501.0,
            689.0,
            909.0,
            23895.0
        ],
        "bins": [
            -0.0016768128843978047,
            -0.0016506126848980784,
            -0.0016244124853983521,
            -0.0015982122858986259,
            -0.0015720120863988996,
            -0.0015458118868991733,
            -0.001519611687399447,
            -0.0014934114878997207,
            -0.0014672112883999944,
            -0.001441011088900268,
            -0.0014148108894005418,
            -0.0013886106899008155,
            -0.0013624104904010892,
            -0.001336210290901363,
            -0.0013100100914016366,
            -0.0012838098919019103,
            -0.001257609692402184,
            -0.0012314094929024577,
            -0.0012052092934027314,
            -0.0011790089774876833,
            -0.001152808777987957,
            -0.0011266085784882307,
            -0.0011004083789885044,
            -0.0010742081794887781,
            -0.0010480079799890518,
            -0.0010218077804893255,
            -0.0009956075809895992,
            -0.0009694074396975338,
            -0.0009432072401978076,
            -0.0009170070406980813,
            -0.000890806841198355,
            -0.0008646066416986287,
            -0.0008384064421989024,
            -0.0008122062426991761,
            -0.0007860060431994498,
            -0.0007598058436997235,
            -0.0007336056441999972,
            -0.0007074054447002709,
            -0.0006812051869928837,
            -0.0006550049874931574,
            -0.0006288047879934311,
            -0.0006026045884937048,
            -0.0005764043889939785,
            -0.0005502041894942522,
            -0.0005240039899945259,
            -0.0004978037904947996,
            -0.0004716035909950733,
            -0.000445403391495347,
            -0.00041920319199562073,
            -0.00039300299249589443,
            -0.00036680279299616814,
            -0.00034060259349644184,
            -0.00031440239399671555,
            -0.00028820219449698925,
            -0.00026200199499726295,
            -0.00023580179549753666,
            -0.00020960159599781036,
            -0.00018340139649808407,
            -0.00015720119699835777,
            -0.00013100099749863148,
            -0.00010480079799890518,
            -7.860059849917889e-05,
            -5.240039899945259e-05,
            -2.6200199499726295e-05,
            0.0
        ]
    },
    "parameters/conv1.bias": {
        "_type": "histogram",
        "values": [
            1.0,
            0.0,
            0.0,
            0.0,
            1.0,
            0.0,
            0.0,
            1.0,
            0.0,
            0.0,
            0.0,
            0.0,
            2.0,
            0.0,
            0.0,
            0.0,
            1.0,
            2.0,
            2.0,
            0.0,
            3.0,
            0.0,
            0.0,
            1.0,
            0.0,
            1.0,
            0.0,
            0.0,
            2.0,
            0.0,
            1.0,
            0.0,
            0.0,
            1.0,
            1.0,
            0.0,
            0.0,
            0.0,
            3.0,
            0.0,
            0.0,
            1.0,
            1.0,
            0.0,
            0.0,
            1.0,
            0.0,
            2.0,
            0.0,
            0.0,
            0.0,
            1.0,
            0.0,
            0.0,
            1.0,
            0.0,
            0.0,
            0.0,
            0.0,
            0.0,
            0.0,
            0.0,
            0.0,
            2.0
        ],
        "bins": [
            -0.047323890030384064,
            -0.046173714101314545,
            -0.045023538172245026,
            -0.04387335851788521,
            -0.04272318258881569,
            -0.04157300665974617,
            -0.04042283073067665,
            -0.03927265480160713,
            -0.038122475147247314,
            -0.036972299218177795,
            -0.035822123289108276,
            -0.03467194736003876,
            -0.03352177143096924,
            -0.03237159550189972,
            -0.03122141771018505,
            -0.030071239918470383,
            -0.028921063989400864,
            -0.027770888060331345,
            -0.026620710268616676,
            -0.025470534339547157,
            -0.02432035654783249,
            -0.02317018061876297,
            -0.02202000468969345,
            -0.020869826897978783,
            -0.019719650968909264,
            -0.018569475039839745,
            -0.017419297248125076,
            -0.016269121319055557,
            -0.015118945389986038,
            -0.01396876946091652,
            -0.012818589806556702,
            -0.011668413877487183,
            -0.010518237948417664,
            -0.009368062019348145,
            -0.008217886090278625,
            -0.007067706435918808,
            -0.005917530506849289,
            -0.00476735457777977,
            -0.003617178648710251,
            -0.002467002719640732,
            -0.0013168230652809143,
            -0.00016664713621139526,
            0.0009835287928581238,
            0.002133704721927643,
            0.003283880650997162,
            0.004434056580066681,
            0.005584236234426498,
            0.0067344121634960175,
            0.007884588092565536,
            0.009034764021635056,
            0.010184939950704575,
            0.011335119605064392,
            0.012485295534133911,
            0.01363547146320343,
            0.01478564739227295,
            0.015935823321342468,
            0.017085999250411987,
            0.018236175179481506,
            0.019386351108551025,
            0.02053653448820114,
            0.02168671041727066,
            0.02283688634634018,
            0.0239870622754097,
            0.025137238204479218,
            0.026287414133548737
        ]
    },
    "_runtime": 196.62171506881714,
    "parameters/fc1.bias": {
        "_type": "histogram",
        "values": [
            0.0,
            0.0,
            0.0,
            0.0,
            0.0,
            0.0,
            0.0,
            0.0,
            0.0,
            0.0,
            0.0,
            0.0,
            0.0,
            0.0,
            0.0,
            0.0,
            0.0,
            0.0,
            0.0,
            0.0,
            0.0,
            0.0,
            0.0,
            0.0,
            0.0,
            0.0,
            0.0,
            0.0,
            0.0,
            0.0,
            0.0,
            0.0,
            1.0,
            0.0,
            0.0,
            0.0,
            0.0,
            0.0,
            0.0,
            0.0,
            0.0,
            0.0,
            0.0,
            0.0,
            0.0,
            0.0,
            0.0,
            0.0,
            0.0,
            0.0,
            0.0,
            0.0,
            0.0,
            0.0,
            0.0,
            0.0,
            0.0,
            0.0,
            0.0,
            0.0,
            0.0,
            0.0,
            0.0,
            0.0
        ],
        "bins": [
            0.03976704552769661,
            0.03976704552769661,
            0.03976704552769661,
            0.03976704552769661,
            0.03976704552769661,
            0.03976704552769661,
            0.03976704552769661,
            0.03976704552769661,
            0.03976704552769661,
            0.03976704552769661,
            0.03976704552769661,
            0.03976704552769661,
            0.03976704552769661,
            0.03976704552769661,
            0.03976704552769661,
            0.03976704552769661,
            0.03976704552769661,
            0.03976704552769661,
            0.03976704552769661,
            0.03976704552769661,
            0.03976704552769661,
            0.03976704552769661,
            0.03976704552769661,
            0.03976704552769661,
            0.03976704552769661,
            0.03976704552769661,
            0.03976704552769661,
            0.03976704552769661,
            0.03976704552769661,
            0.03976704552769661,
            0.03976704552769661,
            0.03976704552769661,
            0.03976704552769661,
            0.03976704552769661,
            0.03976704552769661,
            0.03976704552769661,
            0.03976704552769661,
            0.03976704552769661,
            0.03976704552769661,
            0.03976704552769661,
            0.03976704552769661,
            0.03976704552769661,
            0.03976704552769661,
            0.03976704552769661,
            0.03976704552769661,
            0.03976704552769661,
            0.03976704552769661,
            0.03976704552769661,
            0.03976704552769661,
            0.03976704552769661,
            0.03976704552769661,
            0.03976704552769661,
            0.03976704552769661,
            0.03976704552769661,
            0.03976704552769661,
            0.03976704552769661,
            0.03976704552769661,
            0.03976704552769661,
            0.03976704552769661,
            0.03976704552769661,
            0.03976704552769661,
            0.03976704552769661,
            0.03976704552769661,
            0.03976704552769661,
            0.03976704552769661
        ]
    },
    "gradients/conv1.weight": {
        "_type": "histogram",
        "values": [
            1.0,
            0.0,
            5.0,
            3.0,
            9.0,
            3.0,
            6.0,
            10.0,
            16.0,
            22.0,
            21.0,
            20.0,
            39.0,
            52.0,
            68.0,
            88.0,
            141.0,
            230.0,
            381.0,
            552.0,
            876.0,
            1441.0,
            3071.0,
            17106.0,
            7007.0,
            2186.0,
            1122.0,
            554.0,
            364.0,
            240.0,
            168.0,
            117.0,
            91.0,
            64.0,
            45.0,
            29.0,
            32.0,
            25.0,
            16.0,
            11.0,
            10.0,
            11.0,
            5.0,
            7.0,
            3.0,
            0.0,
            2.0,
            5.0,
            2.0,
            0.0,
            2.0,
            1.0,
            2.0,
            0.0,
            0.0,
            0.0,
            2.0,
            2.0,
            0.0,
            0.0,
            0.0,
            0.0,
            0.0,
            2.0
        ],
        "bins": [
            -0.00037245493149384856,
            -0.00035679913708008826,
            -0.00034114334266632795,
            -0.00032548754825256765,
            -0.00030983175383880734,
            -0.00029417595942504704,
            -0.00027852016501128674,
            -0.00026286437059752643,
            -0.0002472085761837661,
            -0.00023155278177000582,
            -0.00021589698735624552,
            -0.0002002411929424852,
            -0.0001845853985287249,
            -0.0001689296041149646,
            -0.0001532738097012043,
            -0.000137618015287444,
            -0.00012196222087368369,
            -0.00010630642645992339,
            -9.065063204616308e-05,
            -7.499483763240278e-05,
            -5.933904321864247e-05,
            -4.368324880488217e-05,
            -2.8027454391121864e-05,
            -1.237165997736156e-05,
            3.2841344363987446e-06,
            1.893992885015905e-05,
            3.4595723263919353e-05,
            5.025151767767966e-05,
            6.590731209143996e-05,
            8.156310650520027e-05,
            9.721890091896057e-05,
            0.00011287469533272088,
            0.00012853048974648118,
            0.00014418625505641103,
            0.0001598420785740018,
            0.00017549790209159255,
            0.0001911536674015224,
            0.00020680943271145225,
            0.000222465256229043,
            0.00023812107974663377,
            0.0002537768450565636,
            0.00026943261036649346,
            0.0002850884338840842,
            0.000300744257401675,
            0.00031640002271160483,
            0.0003320557880215347,
            0.00034771161153912544,
            0.0003633674350567162,
            0.00037902320036664605,
            0.0003946789656765759,
            0.00041033478919416666,
            0.0004259906127117574,
            0.00044164637802168727,
            0.0004573021433316171,
            0.0004729579668492079,
            0.0004886137903667986,
            0.0005042695556767285,
            0.0005199253209866583,
            0.0005355811445042491,
            0.0005512369680218399,
            0.0005668927333317697,
            0.0005825484986416996,
            0.0005982043221592903,
            0.0006138601456768811,
            0.0006295159109868109
        ]
    },
    "parameters/conv2.bias": {
        "_type": "histogram",
        "values": [
            1.0,
            0.0,
            0.0,
            0.0,
            1.0,
            2.0,
            0.0,
            2.0,
            0.0,
            2.0,
            1.0,
            0.0,
            0.0,
            1.0,
            0.0,
            0.0,
            4.0,
            1.0,
            3.0,
            1.0,
            3.0,
            1.0,
            3.0,
            0.0,
            1.0,
            1.0,
            0.0,
            1.0,
            1.0,
            2.0,
            3.0,
            1.0,
            2.0,
            0.0,
            1.0,
            1.0,
            2.0,
            1.0,
            2.0,
            0.0,
            2.0,
            0.0,
            1.0,
            0.0,
            2.0,
            3.0,
            3.0,
            2.0,
            0.0,
            0.0,
            1.0,
            0.0,
            0.0,
            0.0,
            1.0,
            0.0,
            0.0,
            1.0,
            1.0,
            1.0,
            0.0,
            0.0,
            0.0,
            1.0
        ],
        "bins": [
            -0.05625254660844803,
            -0.054790809750556946,
            -0.053329069167375565,
            -0.05186733230948448,
            -0.0504055917263031,
            -0.04894385486841202,
            -0.047482118010520935,
            -0.04602038115262985,
            -0.04455864056944847,
            -0.04309689998626709,
            -0.04163516312837601,
            -0.040173426270484924,
            -0.03871168941259384,
            -0.03724994882941246,
            -0.03578821197152138,
            -0.034326471388339996,
            -0.032864734530448914,
            -0.03140299767255783,
            -0.02994125708937645,
            -0.028479520231485367,
            -0.027017781510949135,
            -0.025556042790412903,
            -0.02409430593252182,
            -0.02263256534934044,
            -0.021170828491449356,
            -0.019709091633558273,
            -0.018247351050376892,
            -0.01678561419248581,
            -0.015323877334594727,
            -0.013862136751413345,
            -0.012400399893522263,
            -0.010938659310340881,
            -0.009476922452449799,
            -0.008015185594558716,
            -0.006553445011377335,
            -0.005091708153486252,
            -0.0036299675703048706,
            -0.002168230712413788,
            -0.0007064938545227051,
            0.0007552467286586761,
            0.002216983586549759,
            0.0036787204444408417,
            0.005140461027622223,
            0.006602197885513306,
            0.008063934743404388,
            0.009525671601295471,
            0.010987415909767151,
            0.012449152767658234,
            0.013910889625549316,
            0.0153726264834404,
            0.016834363341331482,
            0.01829610764980316,
            0.019757844507694244,
            0.021219581365585327,
            0.02268131822347641,
            0.024143055081367493,
            0.025604791939258575,
            0.027066536247730255,
            0.028528273105621338,
            0.02999000996351242,
            0.0314517468214035,
            0.032913483679294586,
            0.034375227987766266,
            0.03583696484565735,
            0.03729870170354843
        ]
    },
    "gradients/conv2.weight": {
        "_type": "histogram",
        "values": [
            1.0,
            0.0,
            0.0,
            0.0,
            0.0,
            0.0,
            0.0,
            0.0,
            0.0,
            2.0,
            3.0,
            2.0,
            9.0,
            7.0,
            8.0,
            10.0,
            18.0,
            10.0,
            33.0,
            27.0,
            31.0,
            65.0,
            81.0,
            118.0,
            143.0,
            166.0,
            241.0,
            319.0,
            481.0,
            656.0,
            973.0,
            1476.0,
            2305.0,
            3678.0,
            5888.0,
            10056.0,
            12503.0,
            5634.0,
            3420.0,
            2211.0,
            1450.0,
            964.0,
            643.0,
            472.0,
            307.0,
            208.0,
            176.0,
            126.0,
            96.0,
            75.0,
            63.0,
            36.0,
            25.0,
            21.0,
            15.0,
            8.0,
            13.0,
            7.0,
            5.0,
            1.0,
            4.0,
            4.0,
            1.0,
            1.0
        ],
        "bins": [
            -0.00032036853372119367,
            -0.0003115031577181071,
            -0.00030263778171502054,
            -0.00029377243481576443,
            -0.00028490705881267786,
            -0.0002760416828095913,
            -0.0002671763068065047,
            -0.00025831093080341816,
            -0.0002494455548003316,
            -0.00024058020790107548,
            -0.00023171483189798892,
            -0.00022284945589490235,
            -0.00021398407989181578,
            -0.00020511871844064444,
            -0.00019625334243755788,
            -0.00018738798098638654,
            -0.00017852260498329997,
            -0.0001696572289802134,
            -0.00016079186752904207,
            -0.0001519264915259555,
            -0.00014306113007478416,
            -0.0001341957540716976,
            -0.00012533037806861103,
            -0.00011646501661743969,
            -0.00010759964061435312,
            -9.873426461126655e-05,
            -8.986890316009521e-05,
            -8.100352715700865e-05,
            -7.213815115392208e-05,
            -6.327277515083551e-05,
            -5.4407428251579404e-05,
            -4.554205224849284e-05,
            -3.667667624540627e-05,
            -2.7811300242319703e-05,
            -1.8945924239233136e-05,
            -1.0080577339977026e-05,
            -1.215201336890459e-06,
            7.650174666196108e-06,
            1.6515550669282675e-05,
            2.5380926672369242e-05,
            3.424627357162535e-05,
            4.311164957471192e-05,
            5.1977025577798486e-05,
            6.084240158088505e-05,
            6.970777758397162e-05,
            7.857315358705819e-05,
            8.74385004863143e-05,
            9.630387648940086e-05,
            0.00010516925249248743,
            0.000114034628495574,
            0.00012290000449866056,
            0.00013176535139791667,
            0.00014063072740100324,
            0.0001494961034040898,
            0.00015836147940717638,
            0.00016722685541026294,
            0.0001760922314133495,
            0.00018495760741643608,
            0.00019382298341952264,
            0.0002026883012149483,
            0.00021155367721803486,
            0.00022041905322112143,
            0.000229284429224208,
            0.00023814980522729456,
            0.00024701518123038113
        ]
    },
    "gradients/conv2.bias": {
        "_type": "histogram",
        "values": [
            1.0,
            0.0,
            0.0,
            0.0,
            0.0,
            0.0,
            0.0,
            0.0,
            0.0,
            1.0,
            0.0,
            2.0,
            1.0,
            0.0,
            0.0,
            0.0,
            0.0,
            0.0,
            1.0,
            0.0,
            0.0,
            2.0,
            1.0,
            2.0,
            1.0,
            1.0,
            3.0,
            4.0,
            3.0,
            2.0,
            5.0,
            6.0,
            3.0,
            1.0,
            0.0,
            3.0,
            2.0,
            4.0,
            3.0,
            1.0,
            1.0,
            3.0,
            0.0,
            1.0,
            1.0,
            0.0,
            1.0,
            0.0,
            2.0,
            0.0,
            1.0,
            0.0,
            0.0,
            0.0,
            0.0,
            0.0,
            0.0,
            0.0,
            0.0,
            0.0,
            0.0,
            0.0,
            0.0,
            1.0
        ],
        "bins": [
            -0.0014315005391836166,
            -0.0013860180042684078,
            -0.0013405355857685208,
            -0.0012950531672686338,
            -0.001249570632353425,
            -0.0012040880974382162,
            -0.0011586056789383292,
            -0.0011131232604384422,
            -0.0010676407255232334,
            -0.0010221581906080246,
            -0.0009766757721081376,
            -0.0009311932954005897,
            -0.0008857108186930418,
            -0.0008402283419854939,
            -0.000794745865277946,
            -0.0007492633885703981,
            -0.0007037809118628502,
            -0.0006582984351553023,
            -0.0006128159584477544,
            -0.0005673334817402065,
            -0.0005218510050326586,
            -0.0004763685283251107,
            -0.00043088605161756277,
            -0.0003854036331176758,
            -0.00033992109820246696,
            -0.00029443856328725815,
            -0.00024895614478737116,
            -0.00020347372628748417,
            -0.00015799119137227535,
            -0.00011250865645706654,
            -6.702623795717955e-05,
            -2.1543819457292557e-05,
            2.393871545791626e-05,
            6.942125037312508e-05,
            0.00011490366887301207,
            0.00016038608737289906,
            0.00020586862228810787,
            0.0002513511572033167,
            0.0002968335757032037,
            0.00034231599420309067,
            0.0003877985291182995,
            0.0004332810640335083,
            0.0004787634825333953,
            0.0005242459010332823,
            0.0005697284359484911,
            0.0006152109708636999,
            0.0006606932729482651,
            0.0007061758078634739,
            0.0007516583427786827,
            0.0007971408776938915,
            0.0008426234126091003,
            0.0008881057146936655,
            0.0009335882496088743,
            0.0009790707845240831,
            0.0010245530866086483,
            0.0010700356215238571,
            0.001115518156439066,
            0.0011610006913542747,
            0.0012064832262694836,
            0.0012519655283540487,
            0.0012974480632692575,
            0.0013429305981844664,
            0.0013884129002690315,
            0.0014338954351842403,
            0.0014793779700994492
        ]
    },
    "gradients/conv3.bias": {
        "_type": "histogram",
        "values": [
            1.0,
            0.0,
            0.0,
            0.0,
            0.0,
            0.0,
            0.0,
            0.0,
            0.0,
            0.0,
            0.0,
            0.0,
            1.0,
            2.0,
            2.0,
            3.0,
            2.0,
            3.0,
            6.0,
            3.0,
            4.0,
            7.0,
            3.0,
            3.0,
            13.0,
            4.0,
            25.0,
            5.0,
            4.0,
            3.0,
            8.0,
            4.0,
            6.0,
            3.0,
            2.0,
            4.0,
            1.0,
            1.0,
            1.0,
            0.0,
            0.0,
            0.0,
            3.0,
            0.0,
            0.0,
            0.0,
            0.0,
            0.0,
            0.0,
            0.0,
            0.0,
            0.0,
            0.0,
            0.0,
            0.0,
            0.0,
            0.0,
            0.0,
            0.0,
            0.0,
            0.0,
            0.0,
            0.0,
            1.0
        ],
        "bins": [
            -0.0032873335294425488,
            -0.0031647635623812675,
            -0.0030421935953199863,
            -0.002919623628258705,
            -0.002797053661197424,
            -0.0026744836941361427,
            -0.002551913494244218,
            -0.0024293435271829367,
            -0.0023067735601216555,
            -0.0021842035930603743,
            -0.002061633625999093,
            -0.00193906354252249,
            -0.0018164935754612088,
            -0.0016939236083999276,
            -0.0015713535249233246,
            -0.0014487835578620434,
            -0.0013262135908007622,
            -0.001203643623739481,
            -0.0010810736566781998,
            -0.0009585036896169186,
            -0.0008359337225556374,
            -0.0007133635226637125,
            -0.0005907935556024313,
            -0.0004682235885411501,
            -0.0003456536214798689,
            -0.00022308365441858768,
            -0.00010051368735730648,
            2.2056279703974724e-05,
            0.00014462647959589958,
            0.0002671964466571808,
            0.000389766413718462,
            0.0005123363807797432,
            0.0006349063478410244,
            0.0007574763149023056,
            0.0008800462819635868,
            0.001002616249024868,
            0.0011251862160861492,
            0.0012477561831474304,
            0.0013703261502087116,
            0.0014928961172699928,
            0.001615466084331274,
            0.0017380365170538425,
            0.0018606064841151237,
            0.001983176451176405,
            0.002105746418237686,
            0.0022283163852989674,
            0.0023508863523602486,
            0.0024734563194215298,
            0.002596026286482811,
            0.002718596253544092,
            0.0028411662206053734,
            0.0029637361876666546,
            0.003086306154727936,
            0.003208876121789217,
            0.003331446088850498,
            0.0034540160559117794,
            0.003576586488634348,
            0.003699156455695629,
            0.0038217264227569103,
            0.0039442963898181915,
            0.004066866356879473,
            0.004189436323940754,
            0.004312006291002035,
            0.004434576258063316,
            0.0045571462251245975
        ]
    },
    "parameters/fc1.weight": {
        "_type": "histogram",
        "values": [
            3.0,
            9.0,
            18.0,
            45.0,
            125.0,
            367.0,
            415.0,
            485.0,
            520.0,
            570.0,
            578.0,
            573.0,
            585.0,
            617.0,
            574.0,
            615.0,
            655.0,
            594.0,
            602.0,
            594.0,
            613.0,
            591.0,
            634.0,
            622.0,
            595.0,
            636.0,
            638.0,
            564.0,
            627.0,
            671.0,
            606.0,
            722.0,
            628.0,
            666.0,
            657.0,
            603.0,
            616.0,
            602.0,
            615.0,
            581.0,
            637.0,
            629.0,
            627.0,
            658.0,
            617.0,
            662.0,
            592.0,
            599.0,
            577.0,
            369.0,
            171.0,
            123.0,
            88.0,
            66.0,
            52.0,
            36.0,
            29.0,
            22.0,
            20.0,
            11.0,
            7.0,
            11.0,
            7.0,
            7.0
        ],
        "bins": [
            -0.017854327335953712,
            -0.01719430275261402,
            -0.01653427816927433,
            -0.015874255448579788,
            -0.015214230865240097,
            -0.014554206281900406,
            -0.013894181698560715,
            -0.013234157115221024,
            -0.012574133463203907,
            -0.01191410981118679,
            -0.0112540852278471,
            -0.010594060644507408,
            -0.009934036061167717,
            -0.0092740124091506,
            -0.00861398782581091,
            -0.007953964173793793,
            -0.0072939395904541016,
            -0.00663391500711441,
            -0.005973891355097294,
            -0.005313866771757603,
            -0.004653843119740486,
            -0.003993818536400795,
            -0.003333793953061104,
            -0.0026737703010439873,
            -0.0020137447863817215,
            -0.0013537220656871796,
            -0.0006936974823474884,
            -3.367289900779724e-05,
            0.0006263516843318939,
            0.001286376267671585,
            0.001946398988366127,
            0.002606423571705818,
            0.0032664481550455093,
            0.0039264727383852005,
            0.004586497321724892,
            0.005246520042419434,
            0.005906544625759125,
            0.006566569209098816,
            0.007226593792438507,
            0.007886618375778198,
            0.00854664109647274,
            0.009206665679812431,
            0.009866690263152122,
            0.010526714846491814,
            0.011186739429831505,
            0.011846764013171196,
            0.012506786733865738,
            0.013166811317205429,
            0.01382683776319027,
            0.014486858621239662,
            0.015146883204579353,
            0.015806907787919044,
            0.016466932371258736,
            0.017126956954598427,
            0.017786981537938118,
            0.01844700612127781,
            0.0191070307046175,
            0.01976705528795719,
            0.020427079871296883,
            0.021087100729346275,
            0.021747125312685966,
            0.022407149896025658,
            0.02306717447936535,
            0.02372719906270504,
            0.02438722364604473
        ]
    },
    "parameters/conv2.weight": {
        "_type": "histogram",
        "values": [
            4.0,
            5.0,
            23.0,
            53.0,
            178.0,
            792.0,
            953.0,
            967.0,
            957.0,
            995.0,
            967.0,
            1022.0,
            990.0,
            988.0,
            1013.0,
            952.0,
            975.0,
            915.0,
            896.0,
            893.0,
            927.0,
            919.0,
            967.0,
            1001.0,
            968.0,
            953.0,
            970.0,
            930.0,
            968.0,
            981.0,
            974.0,
            911.0,
            958.0,
            944.0,
            966.0,
            932.0,
            950.0,
            997.0,
            961.0,
            909.0,
            1046.0,
            933.0,
            932.0,
            975.0,
            991.0,
            968.0,
            937.0,
            994.0,
            1006.0,
            999.0,
            953.0,
            991.0,
            988.0,
            929.0,
            950.0,
            954.0,
            993.0,
            916.0,
            972.0,
            945.0,
            942.0,
            874.0,
            468.0,
            16.0
        ],
        "bins": [
            -0.057078953832387924,
            -0.05540770664811134,
            -0.05373645946383476,
            -0.05206520855426788,
            -0.0503939613699913,
            -0.04872271418571472,
            -0.04705146700143814,
            -0.04538021981716156,
            -0.04370897263288498,
            -0.0420377254486084,
            -0.04036647826433182,
            -0.03869523108005524,
            -0.03702398017048836,
            -0.03535273298621178,
            -0.033681485801935196,
            -0.03201023489236832,
            -0.030338989570736885,
            -0.028667742386460304,
            -0.026996493339538574,
            -0.025325246155261993,
            -0.023653998970985413,
            -0.021982751786708832,
            -0.02031150460243225,
            -0.01864025369286537,
            -0.01696900650858879,
            -0.01529775932431221,
            -0.01362651214003563,
            -0.011955264955759048,
            -0.010284017771482468,
            -0.008612766861915588,
            -0.006941519677639008,
            -0.005270272493362427,
            -0.003599025309085846,
            -0.0019277781248092651,
            -0.0002565309405326843,
            0.0014147162437438965,
            0.0030859671533107758,
            0.004757214337587357,
            0.006428461521863937,
            0.008099708706140518,
            0.009770955890417099,
            0.01144220307469368,
            0.01311345025897026,
            0.014784697443246841,
            0.016455944627523422,
            0.0181271992623806,
            0.01979844644665718,
            0.02146969363093376,
            0.023140940815210342,
            0.024812187999486923,
            0.026483435183763504,
            0.028154682368040085,
            0.029825929552316666,
            0.031497176736593246,
            0.03316842392086983,
            0.03483967110514641,
            0.03651091828942299,
            0.03818216547369957,
            0.03985342010855675,
            0.04152466729283333,
            0.04319591447710991,
            0.04486716166138649,
            0.04653840884566307,
            0.04820965602993965,
            0.04988090321421623
        ]
    },
    "parameters/conv1.weight": {
        "_type": "histogram",
        "values": [
            2.0,
            0.0,
            0.0,
            4.0,
            2.0,
            4.0,
            23.0,
            307.0,
            717.0,
            672.0,
            618.0,
            668.0,
            657.0,
            639.0,
            604.0,
            652.0,
            627.0,
            672.0,
            635.0,
            640.0,
            640.0,
            657.0,
            592.0,
            674.0,
            649.0,
            635.0,
            590.0,
            625.0,
            676.0,
            637.0,
            669.0,
            654.0,
            644.0,
            667.0,
            670.0,
            637.0,
            615.0,
            627.0,
            660.0,
            677.0,
            668.0,
            652.0,
            637.0,
            644.0,
            679.0,
            617.0,
            634.0,
            631.0,
            649.0,
            629.0,
            636.0,
            676.0,
            690.0,
            677.0,
            644.0,
            652.0,
            644.0,
            619.0,
            673.0,
            634.0,
            607.0,
            609.0,
            592.0,
            457.0
        ],
        "bins": [
            -0.0696466788649559,
            -0.06769853085279465,
            -0.0657503753900528,
            -0.06380222737789154,
            -0.06185407191514969,
            -0.059905920177698135,
            -0.05795776844024658,
            -0.05600961670279503,
            -0.054061464965343475,
            -0.05211331695318222,
            -0.05016516149044037,
            -0.048217013478279114,
            -0.04626885801553726,
            -0.04432071000337601,
            -0.042372554540634155,
            -0.0404244065284729,
            -0.03847625106573105,
            -0.036528103053569794,
            -0.03457995131611824,
            -0.03263179957866669,
            -0.030683647841215134,
            -0.02873549610376358,
            -0.026787344366312027,
            -0.024839192628860474,
            -0.02289104089140892,
            -0.020942889153957367,
            -0.018994737416505814,
            -0.01704658567905426,
            -0.015098433941602707,
            -0.013150282204151154,
            -0.0112021304666996,
            -0.009253978729248047,
            -0.0073058269917964935,
            -0.00535767525434494,
            -0.0034095272421836853,
            -0.0014613717794418335,
            0.0004867762327194214,
            0.002434931695461273,
            0.004383079707622528,
            0.00633123517036438,
            0.008279383182525635,
            0.010227538645267487,
            0.012175686657428741,
            0.014123842120170593,
            0.016071990132331848,
            0.0180201455950737,
            0.019968293607234955,
            0.021916449069976807,
            0.02386459708213806,
            0.025812752544879913,
            0.027760900557041168,
            0.02970905601978302,
            0.031657204031944275,
            0.03360535949468613,
            0.03555350750684738,
            0.03750166296958923,
            0.03944981098175049,
            0.04139796644449234,
            0.043346114456653595,
            0.04529426991939545,
            0.0472424179315567,
            0.04919057339429855,
            0.05113872140645981,
            0.05308687686920166,
            0.055035024881362915
        ]
    },
    "_timestamp": 1579644238.6674428,
    "_step": 0,
    "parameters/conv3.weight": {
        "_type": "histogram",
        "values": [
            3.0,
            6.0,
            26.0,
            80.0,
            213.0,
            637.0,
            3041.0,
            3902.0,
            3874.0,
            3844.0,
            3786.0,
            3834.0,
            3771.0,
            3795.0,
            3893.0,
            3917.0,
            3834.0,
            3936.0,
            3957.0,
            3776.0,
            3935.0,
            3806.0,
            3930.0,
            3891.0,
            3805.0,
            3827.0,
            3798.0,
            3846.0,
            3837.0,
            3849.0,
            3861.0,
            3886.0,
            3777.0,
            3877.0,
            3853.0,
            3834.0,
            3886.0,
            3903.0,
            3817.0,
            3833.0,
            3953.0,
            3895.0,
            3844.0,
            3853.0,
            3929.0,
            3900.0,
            3879.0,
            3888.0,
            3958.0,
            3753.0,
            3795.0,
            3818.0,
            3755.0,
            3921.0,
            3921.0,
            3806.0,
            3836.0,
            3956.0,
            3686.0,
            3797.0,
            3859.0,
            3640.0,
            3319.0,
            2047.0
        ],
        "bins": [
            -0.041653089225292206,
            -0.0404689721763134,
            -0.039284855127334595,
            -0.03810073807835579,
            -0.036916621029376984,
            -0.03573250398039818,
            -0.03454838693141937,
            -0.033364273607730865,
            -0.03218015283346176,
            -0.030996037647128105,
            -0.0298119205981493,
            -0.028627805411815643,
            -0.027443688362836838,
            -0.026259571313858032,
            -0.025075454264879227,
            -0.02389133721590042,
            -0.022707220166921616,
            -0.02152310311794281,
            -0.020338986068964005,
            -0.0191548690199852,
            -0.017970751971006393,
            -0.016786636784672737,
            -0.015602519735693932,
            -0.014418402686715126,
            -0.01323428563773632,
            -0.012050168588757515,
            -0.01086605153977871,
            -0.009681936353445053,
            -0.008497819304466248,
            -0.007313702255487442,
            -0.0061295852065086365,
            -0.004945468157529831,
            -0.0037613511085510254,
            -0.00257723405957222,
            -0.0013931170105934143,
            -0.00020899996161460876,
            0.0009751170873641968,
            0.0021592341363430023,
            0.003343351185321808,
            0.004527468234300613,
            0.005711585283279419,
            0.006895698606967926,
            0.008079815655946732,
            0.009263932704925537,
            0.010448049753904343,
            0.011632166802883148,
            0.012816283851861954,
            0.01400040090084076,
            0.015184517949819565,
            0.01636863499879837,
            0.017552752047777176,
            0.01873686909675598,
            0.019920986145734787,
            0.021105103194713593,
            0.0222892165184021,
            0.023473337292671204,
            0.02465745061635971,
            0.025841571390628815,
            0.027025684714317322,
            0.028209805488586426,
            0.029393918812274933,
            0.030578039586544037,
            0.031762152910232544,
            0.03294627368450165,
            0.034130387008190155
        ]
    },
    "gradients/fc1.bias": {
        "_type": "histogram",
        "values": [
            0.0,
            0.0,
            0.0,
            0.0,
            0.0,
            0.0,
            0.0,
            0.0,
            0.0,
            0.0,
            0.0,
            0.0,
            0.0,
            0.0,
            0.0,
            0.0,
            0.0,
            0.0,
            0.0,
            0.0,
            0.0,
            0.0,
            0.0,
            0.0,
            0.0,
            0.0,
            0.0,
            0.0,
            0.0,
            0.0,
            0.0,
            0.0,
            1.0,
            0.0,
            0.0,
            0.0,
            0.0,
            0.0,
            0.0,
            0.0,
            0.0,
            0.0,
            0.0,
            0.0,
            0.0,
            0.0,
            0.0,
            0.0,
            0.0,
            0.0,
            0.0,
            0.0,
            0.0,
            0.0,
            0.0,
            0.0,
            0.0,
            0.0,
            0.0,
            0.0,
            0.0,
            0.0,
            0.0,
            0.0
        ],
        "bins": [
            -0.3933809995651245,
            -0.3933809995651245,
            -0.3933809995651245,
            -0.3933809995651245,
            -0.3933809995651245,
            -0.3933809995651245,
            -0.3933809995651245,
            -0.3933809995651245,
            -0.3933809995651245,
            -0.3933809995651245,
            -0.3933809995651245,
            -0.3933809995651245,
            -0.3933809995651245,
            -0.3933809995651245,
            -0.3933809995651245,
            -0.3933809995651245,
            -0.3933809995651245,
            -0.3933809995651245,
            -0.3933809995651245,
            -0.3933809995651245,
            -0.3933809995651245,
            -0.3933809995651245,
            -0.3933809995651245,
            -0.3933809995651245,
            -0.3933809995651245,
            -0.3933809995651245,
            -0.3933809995651245,
            -0.3933809995651245,
            -0.3933809995651245,
            -0.3933809995651245,
            -0.3933809995651245,
            -0.3933809995651245,
            -0.3933809995651245,
            -0.3933809995651245,
            -0.3933809995651245,
            -0.3933809995651245,
            -0.3933809995651245,
            -0.3933809995651245,
            -0.3933809995651245,
            -0.3933809995651245,
            -0.3933809995651245,
            -0.3933809995651245,
            -0.3933809995651245,
            -0.3933809995651245,
            -0.3933809995651245,
            -0.3933809995651245,
            -0.3933809995651245,
            -0.3933809995651245,
            -0.3933809995651245,
            -0.3933809995651245,
            -0.3933809995651245,
            -0.3933809995651245,
            -0.3933809995651245,
            -0.3933809995651245,
            -0.3933809995651245,
            -0.3933809995651245,
            -0.3933809995651245,
            -0.3933809995651245,
            -0.3933809995651245,
            -0.3933809995651245,
            -0.3933809995651245,
            -0.3933809995651245,
            -0.3933809995651245,
            -0.3933809995651245,
            -0.3933809995651245
        ]
    },
    "gradients/conv3.weight": {
        "_type": "histogram",
        "values": [
            3.0,
            2.0,
            1.0,
            1.0,
            5.0,
            4.0,
            5.0,
            8.0,
            9.0,
            15.0,
            12.0,
            27.0,
            57.0,
            73.0,
            94.0,
            132.0,
            188.0,
            300.0,
            483.0,
            759.0,
            1298.0,
            2166.0,
            3959.0,
            7584.0,
            18863.0,
            138637.0,
            28102.0,
            8709.0,
            3955.0,
            2266.0,
            1206.0,
            706.0,
            462.0,
            305.0,
            213.0,
            141.0,
            102.0,
            94.0,
            52.0,
            30.0,
            30.0,
            16.0,
            24.0,
            13.0,
            15.0,
            9.0,
            12.0,
            4.0,
            7.0,
            5.0,
            1.0,
            6.0,
            4.0,
            3.0,
            1.0,
            0.0,
            0.0,
            0.0,
            0.0,
            1.0,
            2.0,
            2.0,
            0.0,
            1.0
        ],
        "bins": [
            -0.0003844326420221478,
            -0.00036947286571376026,
            -0.0003545130603015423,
            -0.00033955328399315476,
            -0.00032459350768476725,
            -0.00030963370227254927,
            -0.00029467392596416175,
            -0.0002797141205519438,
            -0.00026475434424355626,
            -0.00024979456793516874,
            -0.00023483476252295077,
            -0.00021987498621456325,
            -0.0002049151953542605,
            -0.00018995540449395776,
            -0.00017499562818557024,
            -0.0001600358373252675,
            -0.00014507604646496475,
            -0.00013011627015657723,
            -0.00011515646474435925,
            -0.00010019668843597174,
            -8.523688302375376e-05,
            -7.027710671536624e-05,
            -5.5317330406978726e-05,
            -4.035752499476075e-05,
            -2.5397748686373234e-05,
            -1.0437972377985716e-05,
            4.521833034232259e-06,
            1.9481609342619777e-05,
            3.4441385651007295e-05,
            4.940119106322527e-05,
            6.436096737161279e-05,
            7.932077278383076e-05,
            9.428054909221828e-05,
            0.0001092403254006058,
            0.00012420010170899332,
            0.00013915993622504175,
            0.00015411971253342927,
            0.00016907948884181678,
            0.0001840392651502043,
            0.00019899904145859182,
            0.00021395887597464025,
            0.00022891865228302777,
            0.00024387842859141529,
            0.0002588382048998028,
            0.0002737979812081903,
            0.00028875775751657784,
            0.00030371759203262627,
            0.0003186773683410138,
            0.0003336371446494013,
            0.0003485969209577888,
            0.00036355669726617634,
            0.0003785165317822248,
            0.0003934763080906123,
            0.0004084360843989998,
            0.00042339586070738733,
            0.00043835563701577485,
            0.00045331541332416236,
            0.0004682752478402108,
            0.0004832350241485983,
            0.0004981948295608163,
            0.0005131545476615429,
            0.0005281143821775913,
            0.0005430742166936398,
            0.0005580339347943664,
            0.0005729937693104148
        ]
    },
    "parameters/conv3.bias": {
        "_type": "histogram",
        "values": [
            1.0,
            0.0,
            0.0,
            0.0,
            0.0,
            0.0,
            0.0,
            0.0,
            0.0,
            0.0,
            0.0,
            0.0,
            0.0,
            0.0,
            1.0,
            0.0,
            0.0,
            0.0,
            1.0,
            2.0,
            0.0,
            2.0,
            1.0,
            0.0,
            0.0,
            1.0,
            3.0,
            3.0,
            1.0,
            0.0,
            0.0,
            0.0,
            4.0,
            3.0,
            8.0,
            2.0,
            7.0,
            2.0,
            2.0,
            3.0,
            2.0,
            5.0,
            3.0,
            4.0,
            5.0,
            2.0,
            3.0,
            4.0,
            5.0,
            4.0,
            4.0,
            8.0,
            6.0,
            3.0,
            3.0,
            6.0,
            2.0,
            2.0,
            2.0,
            1.0,
            3.0,
            2.0,
            0.0,
            2.0
        ],
        "bins": [
            -0.057159725576639175,
            -0.05624707415699959,
            -0.05533442273736,
            -0.05442177131772041,
            -0.05350911617279053,
            -0.05259646475315094,
            -0.05168381333351135,
            -0.050771161913871765,
            -0.04985851049423218,
            -0.04894585907459259,
            -0.048033207654953,
            -0.047120556235313416,
            -0.04620790481567383,
            -0.04529525339603424,
            -0.044382598251104355,
            -0.04346994683146477,
            -0.04255729541182518,
            -0.04164464399218559,
            -0.040731992572546005,
            -0.03981933742761612,
            -0.03890668600797653,
            -0.037994034588336945,
            -0.03708138316869736,
            -0.03616873174905777,
            -0.03525608032941818,
            -0.034343428909778595,
            -0.03343077749013901,
            -0.03251812607049942,
            -0.03160547465085983,
            -0.030692821368575096,
            -0.02978016808629036,
            -0.028867516666650772,
            -0.027954865247011185,
            -0.027042213827371597,
            -0.02612956240773201,
            -0.025216910988092422,
            -0.024304259568452835,
            -0.02339160442352295,
            -0.022478953003883362,
            -0.021566301584243774,
            -0.020653650164604187,
            -0.0197409987449646,
            -0.018828347325325012,
            -0.017915695905685425,
            -0.01700304076075554,
            -0.01609038934111595,
            -0.015177737921476364,
            -0.014265086501836777,
            -0.01335243508219719,
            -0.012439783662557602,
            -0.011527132242918015,
            -0.010614480823278427,
            -0.00970182940363884,
            -0.008789174258708954,
            -0.007876522839069366,
            -0.006963871419429779,
            -0.006051219999790192,
            -0.005138568580150604,
            -0.004225917160511017,
            -0.0033132657408714294,
            -0.0024006105959415436,
            -0.0014879591763019562,
            -0.0005753077566623688,
            0.00033734366297721863,
            0.001249995082616806
        ]
    }
}
