{
    "graph_0": {
        "_type": "graph",
        "format": "torch",
        "nodes": [
            {
                "name": "pool0",
                "id": 139886289016032,
                "class_name": "MaxPool3d(kernel_size=2, stride=2, padding=0, dilation=1, ceil_mode=False)",
                "parameters": [],
                "output_shape": [
                    [
                        42,
                        42,
                        24,
                        24,
                        24
                    ]
                ],
                "num_parameters": []
            },
            {
                "name": "conv1",
                "id": 139884553419128,
                "class_name": "Conv3d(42, 32, kernel_size=(3, 3, 3), stride=(1, 1, 1), padding=(1, 1, 1))",
                "parameters": [
                    [
                        "weight",
                        [
                            32,
                            42,
                            3,
                            3,
                            3
                        ]
                    ],
                    [
                        "bias",
                        [
                            32
                        ]
                    ]
                ],
                "output_shape": [
                    [
                        42,
                        32,
                        24,
                        24,
                        24
                    ]
                ],
                "num_parameters": [
                    36288,
                    32
                ]
            },
            {
                "name": "pool1",
                "id": 139884757900592,
                "class_name": "MaxPool3d(kernel_size=2, stride=2, padding=0, dilation=1, ceil_mode=False)",
                "parameters": [],
                "output_shape": [
                    [
                        42,
                        32,
                        12,
                        12,
                        12
                    ]
                ],
                "num_parameters": []
            },
            {
                "name": "conv2",
                "id": 139884782864032,
                "class_name": "Conv3d(32, 64, kernel_size=(3, 3, 3), stride=(1, 1, 1), padding=(1, 1, 1))",
                "parameters": [
                    [
                        "weight",
                        [
                            64,
                            32,
                            3,
                            3,
                            3
                        ]
                    ],
                    [
                        "bias",
                        [
                            64
                        ]
                    ]
                ],
                "output_shape": [
                    [
                        42,
                        64,
                        12,
                        12,
                        12
                    ]
                ],
                "num_parameters": [
                    55296,
                    64
                ]
            },
            {
                "name": "pool2",
                "id": 139886124386848,
                "class_name": "MaxPool3d(kernel_size=2, stride=2, padding=0, dilation=1, ceil_mode=False)",
                "parameters": [],
                "output_shape": [
                    [
                        42,
                        64,
                        6,
                        6,
                        6
                    ]
                ],
                "num_parameters": []
            },
            {
                "name": "conv3",
                "id": 139884782897584,
                "class_name": "Conv3d(64, 128, kernel_size=(3, 3, 3), stride=(1, 1, 1), padding=(1, 1, 1))",
                "parameters": [
                    [
                        "weight",
                        [
                            128,
                            64,
                            3,
                            3,
                            3
                        ]
                    ],
                    [
                        "bias",
                        [
                            128
                        ]
                    ]
                ],
                "output_shape": [
                    [
                        42,
                        128,
                        6,
                        6,
                        6
                    ]
                ],
                "num_parameters": [
                    221184,
                    128
                ]
            },
            {
                "name": "fc1",
                "id": 139886264569528,
                "class_name": "Linear(in_features=27648, out_features=2, bias=True)",
                "parameters": [
                    [
                        "weight",
                        [
                            2,
                            27648
                        ]
                    ],
                    [
                        "bias",
                        [
                            2
                        ]
                    ]
                ],
                "output_shape": [
                    [
                        42,
                        2
                    ]
                ],
                "num_parameters": [
                    55296,
                    2
                ]
            }
        ],
        "edges": []
    },
    "AUC": 1.0,
    "parameters/fc1.bias": {
        "_type": "histogram",
        "values": [
            1.0,
            0.0,
            0.0,
            0.0,
            0.0,
            0.0,
            0.0,
            0.0,
            0.0,
            0.0,
            0.0,
            0.0,
            0.0,
            0.0,
            0.0,
            0.0,
            0.0,
            0.0,
            0.0,
            0.0,
            0.0,
            0.0,
            0.0,
            0.0,
            0.0,
            0.0,
            0.0,
            0.0,
            0.0,
            0.0,
            0.0,
            0.0,
            0.0,
            0.0,
            0.0,
            0.0,
            0.0,
            0.0,
            0.0,
            0.0,
            0.0,
            0.0,
            0.0,
            0.0,
            0.0,
            0.0,
            0.0,
            0.0,
            0.0,
            0.0,
            0.0,
            0.0,
            0.0,
            0.0,
            0.0,
            0.0,
            0.0,
            0.0,
            0.0,
            0.0,
            0.0,
            0.0,
            0.0,
            1.0
        ],
        "bins": [
            -0.0037982009816914797,
            -0.0036793160252273083,
            -0.003560430835932493,
            -0.003441545646637678,
            -0.0033226606901735067,
            -0.0032037757337093353,
            -0.0030848905444145203,
            -0.002966005355119705,
            -0.002847120398655534,
            -0.0027282354421913624,
            -0.0026093502528965473,
            -0.0024904650636017323,
            -0.002371580107137561,
            -0.0022526951506733894,
            -0.0021338099613785744,
            -0.0020149247720837593,
            -0.001896039815619588,
            -0.0017771546263247728,
            -0.0016582696698606014,
            -0.00153938471339643,
            -0.001420499524101615,
            -0.0013016143348067999,
            -0.0011827293783426285,
            -0.001063844421878457,
            -0.000944959232583642,
            -0.0008260740432888269,
            -0.0007071890868246555,
            -0.0005883041303604841,
            -0.00046941894106566906,
            -0.000350533751770854,
            -0.0002316487953066826,
            -0.00011276383884251118,
            6.121350452303886e-06,
            0.00012500653974711895,
            0.000243891729041934,
            0.00036277645267546177,
            0.00048166164197027683,
            0.0006005468312650919,
            0.0007194315548986197,
            0.0008383167441934347,
            0.0009572019334882498,
            0.0010760871227830648,
            0.00119497231207788,
            0.0013138570357114077,
            0.0014327422250062227,
            0.0015516274143010378,
            0.0016705121379345655,
            0.0017893973272293806,
            0.0019082825165241957,
            0.0020271677058190107,
            0.002146052895113826,
            0.0022649376187473536,
            0.0023838228080421686,
            0.0025027079973369837,
            0.0026215927209705114,
            0.0027404779102653265,
            0.0028593630995601416,
            0.0029782482888549566,
            0.0030971334781497717,
            0.0032160182017832994,
            0.0033349033910781145,
            0.0034537885803729296,
            0.0035726733040064573,
            0.0036915584933012724,
            0.0038104436825960875
        ]
    },
    "parameters/conv3.weight": {
        "_type": "histogram",
        "values": [
            2.0,
            1.0,
            1.0,
            1.0,
            0.0,
            4.0,
            10.0,
            15.0,
            22.0,
            35.0,
            63.0,
            75.0,
            152.0,
            191.0,
            277.0,
            395.0,
            551.0,
            898.0,
            1295.0,
            1814.0,
            2569.0,
            3380.0,
            4740.0,
            6591.0,
            9241.0,
            13485.0,
            20189.0,
            33038.0,
            56367.0,
            22705.0,
            12563.0,
            8272.0,
            5654.0,
            4225.0,
            3086.0,
            2278.0,
            1717.0,
            1330.0,
            1041.0,
            716.0,
            588.0,
            419.0,
            292.0,
            236.0,
            181.0,
            130.0,
            95.0,
            74.0,
            63.0,
            32.0,
            26.0,
            15.0,
            14.0,
            5.0,
            8.0,
            7.0,
            0.0,
            5.0,
            1.0,
            1.0,
            1.0,
            0.0,
            0.0,
            2.0
        ],
        "bins": [
            -0.09219983220100403,
            -0.08897097408771515,
            -0.08574210852384567,
            -0.0825132504105568,
            -0.07928438484668732,
            -0.07605552673339844,
            -0.07282666862010956,
            -0.06959781050682068,
            -0.0663689449429512,
            -0.06314007937908173,
            -0.05991122126579285,
            -0.05668236315250397,
            -0.05345350131392479,
            -0.05022463947534561,
            -0.04699578136205673,
            -0.043766919523477554,
            -0.040538057684898376,
            -0.0373091958463192,
            -0.03408033400774002,
            -0.03085147589445114,
            -0.027622610330581665,
            -0.024393752217292786,
            -0.021164894104003906,
            -0.01793602854013443,
            -0.01470717042684555,
            -0.011478312313556671,
            -0.008249446749687195,
            -0.005020588636398315,
            -0.001791730523109436,
            0.0014371350407600403,
            0.00466599315404892,
            0.007894858717918396,
            0.011123716831207275,
            0.014352574944496155,
            0.01758144050836563,
            0.02081029862165451,
            0.024039164185523987,
            0.027268022298812866,
            0.030496880412101746,
            0.033725738525390625,
            0.0369546115398407,
            0.04018346965312958,
            0.04341232776641846,
            0.046641185879707336,
            0.049870043992996216,
            0.053098902106285095,
            0.05632777512073517,
            0.05955663323402405,
            0.06278549134731293,
            0.0660143494606018,
            0.06924320757389069,
            0.07247208058834076,
            0.07570093870162964,
            0.07892979681491852,
            0.0821586549282074,
            0.08538751304149628,
            0.08861637115478516,
            0.09184524416923523,
            0.09507410228252411,
            0.09830296039581299,
            0.10153181850910187,
            0.10476067662239075,
            0.10798954963684082,
            0.1112184077501297,
            0.11444726586341858
        ]
    },
    "Train Accuracy": 0.6804812088769934,
    "_timestamp": 1579216173.9616024,
    "gradients/conv3.weight": {
        "_type": "histogram",
        "values": [
            1.0,
            1.0,
            1.0,
            2.0,
            0.0,
            2.0,
            2.0,
            7.0,
            3.0,
            2.0,
            9.0,
            9.0,
            15.0,
            19.0,
            27.0,
            53.0,
            66.0,
            126.0,
            170.0,
            306.0,
            537.0,
            1202.0,
            3034.0,
            11085.0,
            149026.0,
            43812.0,
            6872.0,
            2259.0,
            1041.0,
            529.0,
            269.0,
            191.0,
            151.0,
            82.0,
            68.0,
            49.0,
            31.0,
            30.0,
            17.0,
            14.0,
            13.0,
            12.0,
            8.0,
            5.0,
            1.0,
            4.0,
            3.0,
            2.0,
            2.0,
            4.0,
            1.0,
            2.0,
            0.0,
            2.0,
            0.0,
            1.0,
            2.0,
            0.0,
            1.0,
            0.0,
            0.0,
            0.0,
            0.0,
            1.0
        ],
        "bins": [
            -0.04968998581171036,
            -0.04769093170762062,
            -0.045691877603530884,
            -0.043692827224731445,
            -0.04169377312064171,
            -0.03969471901655197,
            -0.03769566863775253,
            -0.035696614533662796,
            -0.03369756042957306,
            -0.03169850632548332,
            -0.029699454084038734,
            -0.027700401842594147,
            -0.02570134773850441,
            -0.023702293634414673,
            -0.021703241392970085,
            -0.019704189151525497,
            -0.01770513504743576,
            -0.015706080943346024,
            -0.013707026839256287,
            -0.011707976460456848,
            -0.009708922356367111,
            -0.007709868252277374,
            -0.005710817873477936,
            -0.003711763769388199,
            -0.001712709665298462,
            0.000286344438791275,
            0.002285398542881012,
            0.0042844489216804504,
            0.006283503025770187,
            0.008282557129859924,
            0.010281607508659363,
            0.0122806616127491,
            0.014279715716838837,
            0.016278766095638275,
            0.01827782392501831,
            0.02027687430381775,
            0.022275932133197784,
            0.024274982511997223,
            0.02627403289079666,
            0.028273090720176697,
            0.030272141098976135,
            0.032271191477775574,
            0.03427024930715561,
            0.03626929968595505,
            0.038268350064754486,
            0.04026740789413452,
            0.04226645827293396,
            0.044265516102313995,
            0.046264566481113434,
            0.04826361685991287,
            0.05026267468929291,
            0.052261725068092346,
            0.05426078289747238,
            0.05625983327627182,
            0.05825888365507126,
            0.060257941484451294,
            0.06225699186325073,
            0.06425604224205017,
            0.0662551000714302,
            0.06825415045022964,
            0.07025320082902908,
            0.07225225865840912,
            0.07425130903720856,
            0.07625036686658859,
            0.07824941724538803
        ]
    },
    "parameters/conv2.bias": {
        "_type": "histogram",
        "values": [
            1.0,
            0.0,
            0.0,
            0.0,
            1.0,
            0.0,
            1.0,
            0.0,
            0.0,
            0.0,
            1.0,
            0.0,
            0.0,
            2.0,
            0.0,
            0.0,
            1.0,
            0.0,
            0.0,
            0.0,
            0.0,
            0.0,
            0.0,
            0.0,
            2.0,
            2.0,
            0.0,
            1.0,
            2.0,
            3.0,
            1.0,
            0.0,
            1.0,
            2.0,
            3.0,
            1.0,
            2.0,
            0.0,
            1.0,
            1.0,
            3.0,
            0.0,
            1.0,
            2.0,
            1.0,
            0.0,
            3.0,
            0.0,
            1.0,
            3.0,
            2.0,
            2.0,
            1.0,
            2.0,
            2.0,
            4.0,
            5.0,
            0.0,
            0.0,
            0.0,
            0.0,
            1.0,
            0.0,
            2.0
        ],
        "bins": [
            -0.49616578221321106,
            -0.4872088134288788,
            -0.4782518744468689,
            -0.4692949056625366,
            -0.46033793687820435,
            -0.45138096809387207,
            -0.4424240291118622,
            -0.4334670603275299,
            -0.42451009154319763,
            -0.41555315256118774,
            -0.40659618377685547,
            -0.3976392149925232,
            -0.3886822462081909,
            -0.37972530722618103,
            -0.37076833844184875,
            -0.3618113696575165,
            -0.3528544306755066,
            -0.3438974618911743,
            -0.33494049310684204,
            -0.32598352432250977,
            -0.3170265555381775,
            -0.3080696165561676,
            -0.2991126477718353,
            -0.29015570878982544,
            -0.28119874000549316,
            -0.2722417712211609,
            -0.2632848024368286,
            -0.25432783365249634,
            -0.24537089467048645,
            -0.23641392588615417,
            -0.2274569571018219,
            -0.218500018119812,
            -0.20954304933547974,
            -0.20058608055114746,
            -0.19162914156913757,
            -0.1826721727848053,
            -0.17371520400047302,
            -0.16475823521614075,
            -0.15580129623413086,
            -0.14684432744979858,
            -0.1378873586654663,
            -0.12893041968345642,
            -0.11997345089912415,
            -0.11101648211479187,
            -0.1020595133304596,
            -0.09310257434844971,
            -0.08414560556411743,
            -0.07518863677978516,
            -0.06623169779777527,
            -0.05727472901344299,
            -0.04831776022911072,
            -0.03936079144477844,
            -0.030403852462768555,
            -0.02144688367843628,
            -0.012489914894104004,
            -0.0035329461097717285,
            0.005423992872238159,
            0.014380961656570435,
            0.02333793044090271,
            0.032294899225234985,
            0.04125186800956726,
            0.05020877718925476,
            0.059165745973587036,
            0.06812271475791931,
            0.07707968354225159
        ]
    },
    "_runtime": 22063.783706188202,
    "Avg Train Loss": 0.013741335831582546,
    "parameters/conv1.weight": {
        "_type": "histogram",
        "values": [
            1.0,
            0.0,
            0.0,
            3.0,
            6.0,
            6.0,
            10.0,
            21.0,
            27.0,
            18.0,
            31.0,
            43.0,
            55.0,
            63.0,
            117.0,
            128.0,
            211.0,
            301.0,
            357.0,
            460.0,
            796.0,
            1219.0,
            1720.0,
            2272.0,
            3292.0,
            5068.0,
            10410.0,
            2896.0,
            1748.0,
            1161.0,
            887.0,
            667.0,
            444.0,
            361.0,
            287.0,
            200.0,
            156.0,
            117.0,
            102.0,
            100.0,
            94.0,
            67.0,
            54.0,
            51.0,
            33.0,
            31.0,
            44.0,
            31.0,
            17.0,
            31.0,
            25.0,
            10.0,
            8.0,
            11.0,
            3.0,
            6.0,
            6.0,
            3.0,
            0.0,
            0.0,
            1.0,
            0.0,
            0.0,
            1.0
        ],
        "bins": [
            -0.19738951325416565,
            -0.18990014493465424,
            -0.18241077661514282,
            -0.1749214231967926,
            -0.1674320548772812,
            -0.15994268655776978,
            -0.15245331823825836,
            -0.14496394991874695,
            -0.13747459650039673,
            -0.12998522818088531,
            -0.1224958598613739,
            -0.11500649899244308,
            -0.10751713067293167,
            -0.10002776980400085,
            -0.09253840148448944,
            -0.08504904061555862,
            -0.07755967229604721,
            -0.0700703114271164,
            -0.06258094310760498,
            -0.05509157478809357,
            -0.04760220646858215,
            -0.040112853050231934,
            -0.03262348473072052,
            -0.025134116411209106,
            -0.017644748091697693,
            -0.01015537977218628,
            -0.0026660263538360596,
            0.004823341965675354,
            0.012312710285186768,
            0.01980207860469818,
            0.0272914320230484,
            0.034780800342559814,
            0.04227016866207123,
            0.04975953698158264,
            0.05724889039993286,
            0.06473827362060547,
            0.07222762703895569,
            0.07971698045730591,
            0.08720636367797852,
            0.09469571709632874,
            0.10218510031700134,
            0.10967445373535156,
            0.11716380715370178,
            0.12465319037437439,
            0.1321425437927246,
            0.13963192701339722,
            0.14712128043174744,
            0.15461063385009766,
            0.16210001707077026,
            0.16958937048912048,
            0.1770787537097931,
            0.1845681071281433,
            0.19205746054649353,
            0.19954684376716614,
            0.20703619718551636,
            0.21452555060386658,
            0.22201493382453918,
            0.2295042872428894,
            0.236993670463562,
            0.24448302388191223,
            0.25197237730026245,
            0.25946176052093506,
            0.2669511139392853,
            0.2744404971599579,
            0.2819298505783081
        ]
    },
    "Avg Test Loss": 0.017918016761541367,
    "gradients/fc1.bias": {
        "_type": "histogram",
        "values": [
            1.0,
            0.0,
            0.0,
            0.0,
            0.0,
            0.0,
            0.0,
            0.0,
            0.0,
            0.0,
            0.0,
            0.0,
            0.0,
            0.0,
            0.0,
            0.0,
            0.0,
            0.0,
            0.0,
            0.0,
            0.0,
            0.0,
            0.0,
            0.0,
            0.0,
            0.0,
            0.0,
            0.0,
            0.0,
            0.0,
            0.0,
            0.0,
            0.0,
            0.0,
            0.0,
            0.0,
            0.0,
            0.0,
            0.0,
            0.0,
            0.0,
            0.0,
            0.0,
            0.0,
            0.0,
            0.0,
            0.0,
            0.0,
            0.0,
            0.0,
            0.0,
            0.0,
            0.0,
            0.0,
            0.0,
            0.0,
            0.0,
            0.0,
            0.0,
            0.0,
            0.0,
            0.0,
            0.0,
            1.0
        ],
        "bins": [
            -0.03006386011838913,
            -0.029124364256858826,
            -0.02818486839532852,
            -0.027245372533798218,
            -0.026305876672267914,
            -0.02536638081073761,
            -0.024426884949207306,
            -0.023487389087677002,
            -0.022547893226146698,
            -0.021608397364616394,
            -0.02066890150308609,
            -0.019729405641555786,
            -0.01878991164267063,
            -0.017850415781140327,
            -0.016910919919610023,
            -0.01597142405807972,
            -0.015031928196549416,
            -0.014092432335019112,
            -0.013152936473488808,
            -0.012213440611958504,
            -0.0112739447504282,
            -0.010334448888897896,
            -0.009394953027367592,
            -0.008455457165837288,
            -0.007515963166952133,
            -0.006576467305421829,
            -0.005636971443891525,
            -0.004697475582361221,
            -0.0037579797208309174,
            -0.0028184838593006134,
            -0.0018789879977703094,
            -0.0009394921362400055,
            3.725290298461914e-09,
            0.0009394995868206024,
            0.0018789954483509064,
            0.0028184913098812103,
            0.0037579871714115143,
            0.004697483032941818,
            0.005636978894472122,
            0.006576474756002426,
            0.00751597061753273,
            0.008455466479063034,
            0.009394962340593338,
            0.010334458202123642,
            0.011273954063653946,
            0.01221344992518425,
            0.013152945786714554,
            0.014092441648244858,
            0.015031933784484863,
            0.015971429646015167,
            0.01691092550754547,
            0.017850421369075775,
            0.01878991723060608,
            0.019729413092136383,
            0.020668908953666687,
            0.02160840481519699,
            0.022547900676727295,
            0.0234873965382576,
            0.024426892399787903,
            0.025366388261318207,
            0.02630588412284851,
            0.027245379984378815,
            0.02818487584590912,
            0.029124371707439423,
            0.030063867568969727
        ]
    },
    "parameters/fc1.weight": {
        "_type": "histogram",
        "values": [
            6.0,
            0.0,
            2.0,
            3.0,
            4.0,
            4.0,
            5.0,
            7.0,
            8.0,
            6.0,
            9.0,
            17.0,
            23.0,
            25.0,
            27.0,
            33.0,
            39.0,
            43.0,
            65.0,
            92.0,
            121.0,
            150.0,
            180.0,
            296.0,
            408.0,
            501.0,
            733.0,
            1040.0,
            1664.0,
            2898.0,
            5274.0,
            13967.0,
            13963.0,
            5276.0,
            2896.0,
            1664.0,
            1040.0,
            734.0,
            500.0,
            408.0,
            296.0,
            180.0,
            150.0,
            121.0,
            92.0,
            65.0,
            43.0,
            39.0,
            33.0,
            27.0,
            25.0,
            23.0,
            17.0,
            9.0,
            6.0,
            8.0,
            7.0,
            5.0,
            4.0,
            4.0,
            3.0,
            2.0,
            0.0,
            6.0
        ],
        "bins": [
            -0.10791736841201782,
            -0.10454494506120682,
            -0.10117252171039581,
            -0.09780009835958481,
            -0.0944276750087738,
            -0.0910552442073822,
            -0.0876828208565712,
            -0.08431039750576019,
            -0.08093797415494919,
            -0.07756555080413818,
            -0.07419312745332718,
            -0.07082070410251617,
            -0.06744827330112457,
            -0.06407585740089417,
            -0.060703426599502563,
            -0.05733100324869156,
            -0.053958579897880554,
            -0.05058615654706955,
            -0.047213733196258545,
            -0.04384130984544754,
            -0.040468886494636536,
            -0.037096455693244934,
            -0.03372403234243393,
            -0.030351608991622925,
            -0.02697918564081192,
            -0.023606762290000916,
            -0.02023433893918991,
            -0.016861915588378906,
            -0.013489484786987305,
            -0.0101170614361763,
            -0.006744638085365295,
            -0.0033722147345542908,
            2.086162567138672e-07,
            0.0033726319670677185,
            0.006745055317878723,
            0.010117478668689728,
            0.013489902019500732,
            0.016862332820892334,
            0.02023474872112274,
            0.023607179522514343,
            0.02697959542274475,
            0.030352026224136353,
            0.033724457025527954,
            0.03709687292575836,
            0.04046930372714996,
            0.04384171962738037,
            0.04721415042877197,
            0.05058656632900238,
            0.05395899713039398,
            0.057331427931785583,
            0.06070384383201599,
            0.06407627463340759,
            0.067448690533638,
            0.0708211213350296,
            0.07419353723526001,
            0.07756596803665161,
            0.08093839883804321,
            0.08431081473827362,
            0.08768324553966522,
            0.09105566143989563,
            0.09442809224128723,
            0.09780050814151764,
            0.10117293894290924,
            0.10454535484313965,
            0.10791778564453125
        ]
    },
    "gradients/conv1.weight": {
        "_type": "histogram",
        "values": [
            1.0,
            0.0,
            1.0,
            0.0,
            0.0,
            2.0,
            1.0,
            1.0,
            3.0,
            3.0,
            2.0,
            6.0,
            3.0,
            5.0,
            6.0,
            1.0,
            3.0,
            2.0,
            5.0,
            1.0,
            7.0,
            6.0,
            8.0,
            2.0,
            9.0,
            10.0,
            17.0,
            31.0,
            61.0,
            84.0,
            122.0,
            161.0,
            189.0,
            220.0,
            266.0,
            382.0,
            819.0,
            1618.0,
            4356.0,
            20262.0,
            3536.0,
            1530.0,
            872.0,
            525.0,
            350.0,
            230.0,
            194.0,
            100.0,
            75.0,
            45.0,
            30.0,
            20.0,
            17.0,
            23.0,
            17.0,
            5.0,
            5.0,
            7.0,
            7.0,
            8.0,
            4.0,
            6.0,
            2.0,
            4.0
        ],
        "bins": [
            -0.06810302287340164,
            -0.06637297570705414,
            -0.06464292854070663,
            -0.06291287392377853,
            -0.06118282675743103,
            -0.05945277959108353,
            -0.05772273242473602,
            -0.05599268525838852,
            -0.05426263436675072,
            -0.052532583475112915,
            -0.05080253630876541,
            -0.04907248914241791,
            -0.047342441976070404,
            -0.0456123910844326,
            -0.0438823439180851,
            -0.042152293026447296,
            -0.04042224586009979,
            -0.03869219869375229,
            -0.03696214780211449,
            -0.03523210063576698,
            -0.03350204974412918,
            -0.03177200257778168,
            -0.030041955411434174,
            -0.02831190451979637,
            -0.026581857353448868,
            -0.024851810187101364,
            -0.023121759295463562,
            -0.02139171212911606,
            -0.019661664962768555,
            -0.017931614071130753,
            -0.01620156690478325,
            -0.014471516013145447,
            -0.012741468846797943,
            -0.01101142168045044,
            -0.009281370788812637,
            -0.007551323622465134,
            -0.0058212727308273315,
            -0.004091225564479828,
            -0.0023611783981323242,
            -0.0006311312317848206,
            0.00109892338514328,
            0.0028289705514907837,
            0.004559017717838287,
            0.006289064884185791,
            0.008019112050533295,
            0.009749159216880798,
            0.011479213833808899,
            0.013209261000156403,
            0.014939308166503906,
            0.01666935533285141,
            0.018399402499198914,
            0.020129457116127014,
            0.021859504282474518,
            0.02358955144882202,
            0.025319598615169525,
            0.02704964578151703,
            0.028779692947864532,
            0.030509747564792633,
            0.03223979473114014,
            0.03396984189748764,
            0.035699889063835144,
            0.03742993623018265,
            0.03915999084711075,
            0.04089003801345825,
            0.042620085179805756
        ]
    },
    "parameters/conv2.weight": {
        "_type": "histogram",
        "values": [
            1.0,
            0.0,
            0.0,
            2.0,
            4.0,
            9.0,
            5.0,
            16.0,
            22.0,
            43.0,
            73.0,
            107.0,
            190.0,
            300.0,
            553.0,
            760.0,
            1209.0,
            1831.0,
            2603.0,
            3428.0,
            4253.0,
            5011.0,
            5383.0,
            5431.0,
            4726.0,
            4193.0,
            3325.0,
            2750.0,
            2117.0,
            1656.0,
            1264.0,
            948.0,
            769.0,
            536.0,
            438.0,
            342.0,
            254.0,
            191.0,
            123.0,
            97.0,
            90.0,
            52.0,
            49.0,
            42.0,
            31.0,
            18.0,
            14.0,
            8.0,
            5.0,
            3.0,
            6.0,
            5.0,
            2.0,
            3.0,
            0.0,
            1.0,
            0.0,
            0.0,
            1.0,
            0.0,
            0.0,
            1.0,
            1.0,
            1.0
        ],
        "bins": [
            -0.14090803265571594,
            -0.13518252968788147,
            -0.129457026720047,
            -0.12373152375221252,
            -0.11800602078437805,
            -0.11228051781654358,
            -0.1065550148487091,
            -0.10082951188087463,
            -0.09510400891304016,
            -0.08937850594520569,
            -0.08365300297737122,
            -0.07792750000953674,
            -0.07220199704170227,
            -0.0664764940738678,
            -0.060750991106033325,
            -0.05502548813819885,
            -0.04929998517036438,
            -0.04357448220252991,
            -0.037848979234695435,
            -0.03212347626686096,
            -0.02639797329902649,
            -0.020672470331192017,
            -0.014946967363357544,
            -0.009221464395523071,
            -0.0034959614276885986,
            0.002229541540145874,
            0.007955044507980347,
            0.01368054747581482,
            0.019406050443649292,
            0.025131553411483765,
            0.030857056379318237,
            0.03658255934715271,
            0.04230806231498718,
            0.048033565282821655,
            0.05375906825065613,
            0.0594845712184906,
            0.06521007418632507,
            0.07093557715415955,
            0.07666108012199402,
            0.08238658308982849,
            0.08811208605766296,
            0.09383758902549744,
            0.09956309199333191,
            0.10528859496116638,
            0.11101409792900085,
            0.11673960089683533,
            0.1224651038646698,
            0.12819060683250427,
            0.13391610980033875,
            0.13964161276817322,
            0.1453671157360077,
            0.15109261870384216,
            0.15681812167167664,
            0.1625436246395111,
            0.16826912760734558,
            0.17399463057518005,
            0.17972013354301453,
            0.185445636510849,
            0.19117113947868347,
            0.19689664244651794,
            0.20262214541435242,
            0.2083476483821869,
            0.21407315135002136,
            0.21979865431785583,
            0.2255241572856903
        ]
    },
    "gradients/conv2.bias": {
        "_type": "histogram",
        "values": [
            1.0,
            0.0,
            0.0,
            0.0,
            0.0,
            1.0,
            0.0,
            0.0,
            0.0,
            0.0,
            0.0,
            1.0,
            0.0,
            1.0,
            0.0,
            0.0,
            0.0,
            0.0,
            1.0,
            1.0,
            0.0,
            1.0,
            2.0,
            0.0,
            3.0,
            1.0,
            2.0,
            2.0,
            1.0,
            0.0,
            1.0,
            0.0,
            0.0,
            2.0,
            1.0,
            3.0,
            3.0,
            0.0,
            1.0,
            1.0,
            3.0,
            2.0,
            3.0,
            5.0,
            2.0,
            2.0,
            4.0,
            1.0,
            1.0,
            1.0,
            2.0,
            1.0,
            0.0,
            0.0,
            1.0,
            0.0,
            0.0,
            1.0,
            0.0,
            2.0,
            2.0,
            0.0,
            0.0,
            1.0
        ],
        "bins": [
            -0.0884074866771698,
            -0.08614455163478851,
            -0.08388161659240723,
            -0.08161868155002594,
            -0.07935574650764465,
            -0.07709281146526337,
            -0.07482987642288208,
            -0.0725669413805008,
            -0.0703040063381195,
            -0.06804107129573822,
            -0.06577813625335693,
            -0.06351520121097565,
            -0.06125226616859436,
            -0.058989331126213074,
            -0.05672639608383179,
            -0.0544634610414505,
            -0.052200525999069214,
            -0.04993759095668793,
            -0.04767465591430664,
            -0.045411720871925354,
            -0.04314878582954407,
            -0.04088585078716278,
            -0.038622915744781494,
            -0.03635998070240021,
            -0.03409704566001892,
            -0.031834110617637634,
            -0.029571175575256348,
            -0.02730824053287506,
            -0.025045305490493774,
            -0.022782370448112488,
            -0.0205194354057312,
            -0.018256500363349915,
            -0.015993565320968628,
            -0.013730630278587341,
            -0.011467695236206055,
            -0.009204760193824768,
            -0.0069418251514434814,
            -0.004678890109062195,
            -0.002415955066680908,
            -0.00015302002429962158,
            0.002109915018081665,
            0.004372850060462952,
            0.006635785102844238,
            0.008898720145225525,
            0.011161655187606812,
            0.013424590229988098,
            0.015687525272369385,
            0.01795046031475067,
            0.020213395357131958,
            0.022476330399513245,
            0.02473926544189453,
            0.027002200484275818,
            0.029265135526657104,
            0.03152807056903839,
            0.03379100561141968,
            0.036053940653800964,
            0.03831687569618225,
            0.04057981073856354,
            0.042842745780944824,
            0.04510568082332611,
            0.0473686158657074,
            0.049631550908088684,
            0.05189448595046997,
            0.05415742099285126,
            0.056420356035232544
        ]
    },
    "Test Precision": 0.5513141751289368,
    "Test Recall": 0.638073742389679,
    "gradients/conv3.bias": {
        "_type": "histogram",
        "values": [
            1.0,
            0.0,
            0.0,
            0.0,
            0.0,
            0.0,
            0.0,
            0.0,
            0.0,
            0.0,
            0.0,
            0.0,
            0.0,
            0.0,
            0.0,
            1.0,
            0.0,
            0.0,
            0.0,
            0.0,
            0.0,
            0.0,
            0.0,
            0.0,
            1.0,
            1.0,
            2.0,
            0.0,
            0.0,
            0.0,
            2.0,
            1.0,
            1.0,
            0.0,
            2.0,
            5.0,
            1.0,
            5.0,
            3.0,
            7.0,
            9.0,
            15.0,
            22.0,
            7.0,
            11.0,
            5.0,
            5.0,
            4.0,
            2.0,
            3.0,
            2.0,
            1.0,
            0.0,
            2.0,
            0.0,
            0.0,
            0.0,
            1.0,
            0.0,
            0.0,
            1.0,
            3.0,
            0.0,
            2.0
        ],
        "bins": [
            -0.13708826899528503,
            -0.1338537186384201,
            -0.13061915338039398,
            -0.12738460302352905,
            -0.12415005266666412,
            -0.1209154948592186,
            -0.11768093705177307,
            -0.11444638669490814,
            -0.11121182888746262,
            -0.10797727853059769,
            -0.10474272072315216,
            -0.10150817036628723,
            -0.0982736125588417,
            -0.09503905475139618,
            -0.09180450439453125,
            -0.08856994658708572,
            -0.0853353887796402,
            -0.08210083842277527,
            -0.07886628806591034,
            -0.07563172280788422,
            -0.07239717245101929,
            -0.06916262209415436,
            -0.06592806428670883,
            -0.0626935064792633,
            -0.059458956122398376,
            -0.05622439831495285,
            -0.05298984795808792,
            -0.049755290150642395,
            -0.04652073234319687,
            -0.04328618198633194,
            -0.040051624178886414,
            -0.036817073822021484,
            -0.03358251601457596,
            -0.030347958207130432,
            -0.027113407850265503,
            -0.023878850042819977,
            -0.020644299685955048,
            -0.01740974187850952,
            -0.014175184071063995,
            -0.01094062626361847,
            -0.00770607590675354,
            -0.004471525549888611,
            -0.0012369751930236816,
            0.0019975900650024414,
            0.005232140421867371,
            0.0084666907787323,
            0.011701256036758423,
            0.014935806393623352,
            0.01817035675048828,
            0.021404922008514404,
            0.024639472365379333,
            0.027874022722244263,
            0.031108573079109192,
            0.034343138337135315,
            0.037577688694000244,
            0.04081223905086517,
            0.044046804308891296,
            0.047281354665756226,
            0.050515905022621155,
            0.05375047028064728,
            0.05698502063751221,
            0.060219570994377136,
            0.06345412135124207,
            0.06668868660926819,
            0.06992323696613312
        ]
    },
    "gradients/conv1.bias": {
        "_type": "histogram",
        "values": [
            1.0,
            0.0,
            1.0,
            0.0,
            0.0,
            0.0,
            1.0,
            0.0,
            1.0,
            3.0,
            0.0,
            0.0,
            0.0,
            1.0,
            0.0,
            0.0,
            0.0,
            0.0,
            0.0,
            1.0,
            0.0,
            0.0,
            0.0,
            0.0,
            0.0,
            0.0,
            3.0,
            0.0,
            1.0,
            1.0,
            1.0,
            2.0,
            2.0,
            1.0,
            0.0,
            0.0,
            1.0,
            0.0,
            1.0,
            1.0,
            1.0,
            0.0,
            0.0,
            1.0,
            1.0,
            1.0,
            0.0,
            0.0,
            1.0,
            0.0,
            1.0,
            0.0,
            0.0,
            1.0,
            0.0,
            0.0,
            0.0,
            0.0,
            1.0,
            0.0,
            0.0,
            0.0,
            0.0,
            1.0
        ],
        "bins": [
            -0.0808912068605423,
            -0.07810482382774353,
            -0.07531843334436417,
            -0.0725320428609848,
            -0.06974565982818604,
            -0.06695927679538727,
            -0.0641728863120079,
            -0.06138649955391884,
            -0.05860011279582977,
            -0.05581372603774071,
            -0.05302733927965164,
            -0.050240952521562576,
            -0.04745456576347351,
            -0.044668179005384445,
            -0.04188179224729538,
            -0.039095405489206314,
            -0.03630901873111725,
            -0.03352263197302818,
            -0.030736245214939117,
            -0.027949858456850052,
            -0.025163471698760986,
            -0.02237708494067192,
            -0.019590698182582855,
            -0.01680430769920349,
            -0.014017924666404724,
            -0.011231541633605957,
            -0.008445151150226593,
            -0.005658760666847229,
            -0.002872377634048462,
            -8.599460124969482e-05,
            0.002700395882129669,
            0.005486786365509033,
            0.0082731693983078,
            0.011059552431106567,
            0.013845942914485931,
            0.016632333397865295,
            0.019418716430664062,
            0.02220509946346283,
            0.024991489946842194,
            0.027777880430221558,
            0.030564263463020325,
            0.03335064649581909,
            0.036137036979198456,
            0.03892342746257782,
            0.04170981049537659,
            0.044496193528175354,
            0.047282591462135315,
            0.05006897449493408,
            0.05285535752773285,
            0.055641740560531616,
            0.05842812359333038,
            0.061214521527290344,
            0.06400090456008911,
            0.06678728759288788,
            0.06957368552684784,
            0.0723600685596466,
            0.07514645159244537,
            0.07793283462524414,
            0.08071921765804291,
            0.08350561559200287,
            0.08629199862480164,
            0.0890783816576004,
            0.09186477959156036,
            0.09465116262435913,
            0.0974375456571579
        ]
    },
    "Test Accuracy": 0.5593894720077515,
    "_step": 99,
    "parameters/conv3.bias": {
        "_type": "histogram",
        "values": [
            1.0,
            0.0,
            1.0,
            0.0,
            1.0,
            1.0,
            0.0,
            0.0,
            0.0,
            0.0,
            2.0,
            0.0,
            1.0,
            0.0,
            0.0,
            0.0,
            0.0,
            1.0,
            2.0,
            0.0,
            0.0,
            0.0,
            1.0,
            0.0,
            1.0,
            2.0,
            2.0,
            1.0,
            2.0,
            2.0,
            0.0,
            1.0,
            0.0,
            2.0,
            1.0,
            1.0,
            3.0,
            1.0,
            3.0,
            1.0,
            3.0,
            0.0,
            4.0,
            6.0,
            4.0,
            7.0,
            5.0,
            5.0,
            6.0,
            9.0,
            8.0,
            6.0,
            4.0,
            8.0,
            8.0,
            3.0,
            4.0,
            0.0,
            0.0,
            1.0,
            1.0,
            0.0,
            0.0,
            2.0
        ],
        "bins": [
            -0.23607009649276733,
            -0.2316938191652298,
            -0.22731754183769226,
            -0.22294126451015472,
            -0.2185649871826172,
            -0.21418870985507965,
            -0.20981243252754211,
            -0.20543615520000458,
            -0.20105987787246704,
            -0.1966836005449295,
            -0.19230732321739197,
            -0.18793104588985443,
            -0.1835547685623169,
            -0.17917849123477936,
            -0.17480221390724182,
            -0.17042593657970428,
            -0.16604965925216675,
            -0.1616733819246292,
            -0.15729710459709167,
            -0.15292082726955414,
            -0.1485445499420166,
            -0.14416827261447906,
            -0.13979199528694153,
            -0.135415717959404,
            -0.13103944063186646,
            -0.12666316330432892,
            -0.12228688597679138,
            -0.11791060864925385,
            -0.11353433132171631,
            -0.10915805399417877,
            -0.10478177666664124,
            -0.1004054993391037,
            -0.09602922201156616,
            -0.09165294468402863,
            -0.08727666735649109,
            -0.08290039002895355,
            -0.07852411270141602,
            -0.07414783537387848,
            -0.06977155804634094,
            -0.0653952807188034,
            -0.06101900339126587,
            -0.05664272606372833,
            -0.052266448736190796,
            -0.04789017140865326,
            -0.04351389408111572,
            -0.039137616753578186,
            -0.03476133942604065,
            -0.030385062098503113,
            -0.026008784770965576,
            -0.02163250744342804,
            -0.017256230115890503,
            -0.012879952788352966,
            -0.00850367546081543,
            -0.004127398133277893,
            0.00024887919425964355,
            0.00462515652179718,
            0.009001433849334717,
            0.013377711176872253,
            0.01775398850440979,
            0.022130250930786133,
            0.026506543159484863,
            0.030882835388183594,
            0.035259097814559937,
            0.03963536024093628,
            0.04401165246963501
        ]
    },
    "gradients/conv2.weight": {
        "_type": "histogram",
        "values": [
            1.0,
            0.0,
            4.0,
            1.0,
            4.0,
            2.0,
            6.0,
            5.0,
            6.0,
            6.0,
            4.0,
            6.0,
            23.0,
            21.0,
            30.0,
            40.0,
            52.0,
            77.0,
            84.0,
            139.0,
            207.0,
            329.0,
            547.0,
            953.0,
            1722.0,
            3354.0,
            7725.0,
            21089.0,
            10291.0,
            3818.0,
            1770.0,
            1052.0,
            673.0,
            380.0,
            257.0,
            178.0,
            128.0,
            85.0,
            61.0,
            36.0,
            30.0,
            24.0,
            14.0,
            15.0,
            11.0,
            8.0,
            3.0,
            6.0,
            3.0,
            3.0,
            1.0,
            2.0,
            1.0,
            1.0,
            0.0,
            1.0,
            0.0,
            1.0,
            2.0,
            0.0,
            2.0,
            0.0,
            0.0,
            2.0
        ],
        "bins": [
            -0.046700336039066315,
            -0.045014262199401855,
            -0.043328188359737396,
            -0.04164211452007294,
            -0.03995603695511818,
            -0.03826996311545372,
            -0.03658388927578926,
            -0.0348978154361248,
            -0.033211737871170044,
            -0.031525664031505585,
            -0.029839590191841125,
            -0.028153516352176666,
            -0.026467442512512207,
            -0.0247813668102026,
            -0.02309529297053814,
            -0.02140921726822853,
            -0.01972314342856407,
            -0.018037069588899612,
            -0.016350993886590004,
            -0.014664918184280396,
            -0.012978844344615936,
            -0.011292770504951477,
            -0.009606696665287018,
            -0.007920622825622559,
            -0.006234548985958099,
            -0.004548471421003342,
            -0.0028623975813388824,
            -0.0011763237416744232,
            0.000509750097990036,
            0.0021958239376544952,
            0.003881901502609253,
            0.005567975342273712,
            0.007254049181938171,
            0.00894012302160263,
            0.01062619686126709,
            0.012312274426221848,
            0.013998348265886307,
            0.015684422105550766,
            0.017370499670505524,
            0.019056573510169983,
            0.020742647349834442,
            0.0224287211894989,
            0.02411479502916336,
            0.02580086886882782,
            0.02748694270849228,
            0.02917301654815674,
            0.030859090387821198,
            0.03254516422748566,
            0.034231238067150116,
            0.03591731935739517,
            0.03760339319705963,
            0.03928946703672409,
            0.04097554087638855,
            0.04266161471605301,
            0.04434768855571747,
            0.04603376239538193,
            0.04771983623504639,
            0.049405910074710846,
            0.051091983914375305,
            0.05277806520462036,
            0.05446413904428482,
            0.05615021288394928,
            0.05783628672361374,
            0.0595223605632782,
            0.06120843440294266
        ]
    },
    "parameters/conv1.bias": {
        "_type": "histogram",
        "values": [
            1.0,
            1.0,
            0.0,
            0.0,
            0.0,
            0.0,
            1.0,
            1.0,
            1.0,
            0.0,
            0.0,
            3.0,
            2.0,
            1.0,
            0.0,
            0.0,
            0.0,
            1.0,
            1.0,
            4.0,
            2.0,
            1.0,
            2.0,
            4.0,
            2.0,
            2.0,
            1.0,
            0.0,
            0.0,
            0.0,
            0.0,
            0.0,
            0.0,
            0.0,
            0.0,
            0.0,
            0.0,
            0.0,
            0.0,
            0.0,
            0.0,
            0.0,
            0.0,
            0.0,
            0.0,
            0.0,
            0.0,
            0.0,
            0.0,
            0.0,
            0.0,
            0.0,
            0.0,
            0.0,
            0.0,
            0.0,
            0.0,
            0.0,
            0.0,
            0.0,
            0.0,
            0.0,
            0.0,
            1.0
        ],
        "bins": [
            -0.31981390714645386,
            -0.30764251947402954,
            -0.2954711318016052,
            -0.2832997441291809,
            -0.2711283564567566,
            -0.25895699858665466,
            -0.24678561091423035,
            -0.23461422324180603,
            -0.2224428355693817,
            -0.2102714478969574,
            -0.19810006022453308,
            -0.18592868745326996,
            -0.17375729978084564,
            -0.16158591210842133,
            -0.1494145393371582,
            -0.1372431516647339,
            -0.12507176399230957,
            -0.11290037631988525,
            -0.10072898864746094,
            -0.08855761587619781,
            -0.0763862282037735,
            -0.06421485543251038,
            -0.05204346776008606,
            -0.03987208008766174,
            -0.027700692415237427,
            -0.01552930474281311,
            -0.003357917070388794,
            0.008813470602035522,
            0.02098482847213745,
            0.03315621614456177,
            0.045327603816986084,
            0.0574989914894104,
            0.06967037916183472,
            0.08184176683425903,
            0.09401315450668335,
            0.10618454217910767,
            0.11835592985153198,
            0.1305272877216339,
            0.14269867539405823,
            0.15487006306648254,
            0.16704145073890686,
            0.17921283841133118,
            0.1913841962814331,
            0.20355558395385742,
            0.21572697162628174,
            0.22789835929870605,
            0.24006974697113037,
            0.2522411346435547,
            0.264412522315979,
            0.2765839099884033,
            0.28875529766082764,
            0.30092668533325195,
            0.31309807300567627,
            0.3252694606781006,
            0.3374408483505249,
            0.3496122360229492,
            0.36178356409072876,
            0.3739549517631531,
            0.3861263394355774,
            0.3982977271080017,
            0.410469114780426,
            0.42264050245285034,
            0.43481189012527466,
            0.446983277797699,
            0.4591546654701233
        ]
    },
    "gradients/fc1.weight": {
        "_type": "histogram",
        "values": [
            1.0,
            1.0,
            0.0,
            1.0,
            2.0,
            3.0,
            0.0,
            3.0,
            2.0,
            0.0,
            2.0,
            1.0,
            0.0,
            4.0,
            5.0,
            6.0,
            4.0,
            5.0,
            11.0,
            10.0,
            17.0,
            18.0,
            34.0,
            40.0,
            65.0,
            87.0,
            163.0,
            280.0,
            445.0,
            910.0,
            2400.0,
            14496.0,
            31760.0,
            2400.0,
            910.0,
            445.0,
            280.0,
            163.0,
            87.0,
            65.0,
            40.0,
            34.0,
            18.0,
            17.0,
            10.0,
            11.0,
            5.0,
            4.0,
            6.0,
            5.0,
            4.0,
            0.0,
            1.0,
            2.0,
            0.0,
            2.0,
            3.0,
            0.0,
            3.0,
            2.0,
            1.0,
            0.0,
            1.0,
            1.0
        ],
        "bins": [
            -0.04380623623728752,
            -0.042437292635440826,
            -0.04106834530830383,
            -0.03969940170645714,
            -0.03833045810461044,
            -0.03696151077747345,
            -0.035592567175626755,
            -0.03422362357378006,
            -0.032854676246643066,
            -0.03148573264479637,
            -0.030116787180304527,
            -0.028747841715812683,
            -0.027378898113965988,
            -0.026009952649474144,
            -0.0246410071849823,
            -0.023272063583135605,
            -0.02190311811864376,
            -0.020534172654151917,
            -0.01916522905230522,
            -0.017796283587813377,
            -0.016427338123321533,
            -0.015058394521474838,
            -0.013689449056982994,
            -0.01232050359249115,
            -0.010951559990644455,
            -0.009582612663507462,
            -0.008213669061660767,
            -0.006844725459814072,
            -0.005475778132677078,
            -0.004106834530830383,
            -0.0027378909289836884,
            -0.001368943601846695,
            0.0,
            0.001368943601846695,
            0.0027378909289836884,
            0.004106834530830383,
            0.005475778132677078,
            0.006844725459814072,
            0.008213669061660767,
            0.009582612663507462,
            0.010951559990644455,
            0.01232050359249115,
            0.013689447194337845,
            0.015058394521474838,
            0.016427338123321533,
            0.017796281725168228,
            0.01916522905230522,
            0.020534176379442215,
            0.02190311625599861,
            0.023272063583135605,
            0.0246410109102726,
            0.026009950786828995,
            0.027378898113965988,
            0.02874784544110298,
            0.030116785317659378,
            0.03148573264479637,
            0.032854679971933365,
            0.03422361984848976,
            0.035592567175626755,
            0.03696151450276375,
            0.038330454379320145,
            0.03969940170645714,
            0.04106834903359413,
            0.04243728891015053,
            0.04380623623728752
        ]
    }
}
